{
  "canonical_id": "881d1ce9754b75350d1ddd55fdec0815",
  "title": "Arteriovenous shunts of the cervical spine: patient demographics, presentation, patterns of high-risk venous drainage, and updated classification",
  "year": 2024,
  "venue": "Journal of NeuroInterventional Surgery",
  "doi": "10.1136/jnis-2023-021353",
  "is_preprint": false,
  "out_of_scope_note": "Clinical neurointerventional surgery paper on cervical-spine arteriovenous shunt classification — vascular/clinical scope, not cognitive/perceptual/computational neuroscience.",
  "claims": [],
  "methods": [],
  "constructs": [],
  "tasks": [],
  "measures": [],
  "models": [],
  "datasets": [],
  "species": [],
  "populations": [],
  "phenomena": [],
  "theories": [],
  "limitations": [],
  "novel_contributions": [],
  "connections": [],
  "keywords": [],
  "coverage": 0.0,
  "synopsis_version": "v1.2026-05-27",
  "generator": "opus-4-7@2026-05-27",
  "generated_at": "2026-05-28T00:11:03+09:00",
  "review_status": "auto_unreviewed",
  "abstract_coverage": 0.0,
  "frameworks": [],
  "key_assumptions": [],
  "manipulations": [],
  "key_findings": [],
  "interpretations": [],
  "limitations_noted": [],
  "connecting_signals": [],
  "core_question": null
}